robodm/__init__.py
robodm/dataset.py
robodm/feature.py
robodm/py.typed
robodm/trajectory.py
robodm/trajectory_base.py
robodm/trajectory_factory.py
robodm/utils.py
robodm/loader/__init__.py
robodm/loader/base.py
robodm/loader/hdf5.py
robodm/loader/rlds.py
robodm/loader/vla.py
robodm-0.1.0.dist-info/licenses/LICENSE
robodm-0.1.0.dist-info/METADATA
robodm-0.1.0.dist-info/WHEEL
robodm-0.1.0.dist-info/top_level.txt
robodm-0.1.0.dist-info/RECORD
