Metadata-Version: 2.4
Name: robodm
Version: 0.1.0
Summary: An Efficient and Scalable Data Collection and Management Framework For Robotics Learning
Author-email: Kaiyuan Chen <kych@berkeley.edu>
Project-URL: homepage, https://github.com/BerkeleyAutomation/robodm/
Project-URL: repository, https://github.com/BerkeleyAutomation/robodm/
Project-URL: documentation, https://github.com/BerkeleyAutomation/robodm/
Project-URL: Bug Tracker, https://github.com/BerkeleyAutomation/robodm/issues
Keywords: robotics,data management,machine learning,trajectories
Classifier: Development Status :: 4 - Beta
Classifier: Intended Audience :: Developers
Classifier: Intended Audience :: Science/Research
Classifier: License :: OSI Approved :: Apache Software License
Classifier: Operating System :: OS Independent
Classifier: Programming Language :: Python :: 3
Classifier: Programming Language :: Python :: 3.10
Classifier: Programming Language :: Python :: 3.11
Classifier: Programming Language :: Python :: 3.12
Classifier: Topic :: Scientific/Engineering :: Artificial Intelligence
Classifier: Topic :: Software Development :: Libraries :: Python Modules
Requires-Python: >=3.10
License-File: LICENSE
Requires-Dist: numpy>=1.21.0
Requires-Dist: h5py>=3.7.0
Requires-Dist: opencv-python>=4.5.0
Requires-Dist: tqdm>=4.64.0
Requires-Dist: psutil>=5.9.0
Requires-Dist: ray[data]>=2.8.0
Provides-Extra: hf
Requires-Dist: datasets>=2.14.0; extra == "hf"
Requires-Dist: huggingface-hub>=0.16.0; extra == "hf"
Provides-Extra: rtx
Requires-Dist: tensorflow>=2.13.0; extra == "rtx"
Requires-Dist: tensorflow-datasets>=4.9.0; extra == "rtx"
Provides-Extra: aws
Requires-Dist: boto3>=1.26.0; extra == "aws"
Requires-Dist: s3fs>=2023.6.0; extra == "aws"
Provides-Extra: torch
Requires-Dist: torch>=1.13.0; extra == "torch"
Requires-Dist: torchvision>=0.14.0; extra == "torch"
Provides-Extra: test
Requires-Dist: pytest>=7.0.0; extra == "test"
Requires-Dist: pytest-cov>=4.0.0; extra == "test"
Requires-Dist: pytest-xdist>=3.0.0; extra == "test"
Requires-Dist: pytest-benchmark>=4.0.0; extra == "test"
Provides-Extra: lerobot
Requires-Dist: lerobot>=0.1.0; extra == "lerobot"
Provides-Extra: all
Requires-Dist: robodm[aws,hf,lerobot,rtx,torch]; extra == "all"
Dynamic: license-file
